odoo/addons/partner_supplierinfo_smartbutton/README.rst
odoo/addons/partner_supplierinfo_smartbutton/__init__.py
odoo/addons/partner_supplierinfo_smartbutton/__manifest__.py
odoo/addons/partner_supplierinfo_smartbutton/i18n/es.po
odoo/addons/partner_supplierinfo_smartbutton/i18n/fr.po
odoo/addons/partner_supplierinfo_smartbutton/i18n/it.po
odoo/addons/partner_supplierinfo_smartbutton/i18n/partner_supplierinfo_smartbutton.pot
odoo/addons/partner_supplierinfo_smartbutton/models/__init__.py
odoo/addons/partner_supplierinfo_smartbutton/models/res_partner.py
odoo/addons/partner_supplierinfo_smartbutton/readme/CONFIGURE.rst
odoo/addons/partner_supplierinfo_smartbutton/readme/CONTRIBUTORS.rst
odoo/addons/partner_supplierinfo_smartbutton/readme/DESCRIPTION.rst
odoo/addons/partner_supplierinfo_smartbutton/readme/INSTALL.rst
odoo/addons/partner_supplierinfo_smartbutton/readme/USAGE.rst
odoo/addons/partner_supplierinfo_smartbutton/static/description/icon.png
odoo/addons/partner_supplierinfo_smartbutton/static/description/index.html
odoo/addons/partner_supplierinfo_smartbutton/tests/__init__.py
odoo/addons/partner_supplierinfo_smartbutton/tests/test_partner_supplierinfo_smartbutton.py
odoo/addons/partner_supplierinfo_smartbutton/views/res_partner_view.xml
odoo14_addon_partner_supplierinfo_smartbutton-14.0.1.0.1.dev8.dist-info/METADATA
odoo14_addon_partner_supplierinfo_smartbutton-14.0.1.0.1.dev8.dist-info/WHEEL
odoo14_addon_partner_supplierinfo_smartbutton-14.0.1.0.1.dev8.dist-info/top_level.txt
odoo14_addon_partner_supplierinfo_smartbutton-14.0.1.0.1.dev8.dist-info/RECORD
